vnscope/__init__.py
vnscope/classify.py
vnscope/core.abi3.so
vnscope/models.py
vnscope/symbols.py
vnscope/util.py
vnscope-1.0.62.dist-info/METADATA
vnscope-1.0.62.dist-info/WHEEL
vnscope-1.0.62.dist-info/RECORD
