Metadata-Version: 2.4
Name: vnscope
Version: 1.0.62
Classifier: Programming Language :: Rust
Classifier: Programming Language :: Python :: Implementation :: CPython
Classifier: Programming Language :: Python :: 3.9
Requires-Dist: seaborn>=0.3
Requires-Dist: pyarrow>=7.0.0
Requires-Dist: polars>=0.36.2
Requires-Dist: mplfinance>=0.12.10b0
Requires-Python: >=3.9
